[
    {
        "date": "Tue Aug 29 04:49:12 +0000 2017",
        "feature": "hashtaghelpinghand",
        "tweet": "RT hashtagbrothers hashtaghelpinghand hashtagsaving hashtagbrotherskeeper hashtaghurricaneharvey hashtagthiscouldbeyou hashtaghouston"
    },
    {
        "date": "Tue Aug 29 04:43:39 +0000 2017",
        "feature": "hashtaghelpinghand",
        "tweet": "hashtagbrothers hashtaghelpinghand hashtagsaving hashtagbrotherskeeper hashtaghurricaneharvey hashtagthiscouldbeyou hashtaghouston"
    }
]